eon_rabbit_client/__init__.py
eon_rabbit_client/channel_controller.py
eon_rabbit_client/connection_controller.py
eon_rabbit_client/consume_controller.py
eon_rabbit_client/exchange_controller.py
eon_rabbit_client/publish_controller.py
eon_rabbit_client/queue_controller.py
eon_rabbit_client-1.0.0.dist-info/METADATA
eon_rabbit_client-1.0.0.dist-info/WHEEL
eon_rabbit_client-1.0.0.dist-info/top_level.txt
eon_rabbit_client-1.0.0.dist-info/RECORD
