Metadata-Version: 2.1
Name: eon-rabbit-client
Version: 1.0.0
Home-page: https://bitbucket.org/eon-mes/broker_utilities/src/master
Author: Ahmad Salameh
Author-email: a.salameh@eonaligner.com
License: MIT
Keywords: eon broker project
Requires-Dist: aio-pika (==8.3.0)
